LICENSE
README.md
setup.py
micropython_ulogger.egg-info/PKG-INFO
micropython_ulogger.egg-info/SOURCES.txt
micropython_ulogger.egg-info/dependency_links.txt
micropython_ulogger.egg-info/top_level.txt
ulogger/__init__.py