Metadata-Version: 1.1
Name: micropython-ulogger
Version: 1.1
Summary: Log module customized for micropython.
Home-page: https://github.com/Li-Lian1069/micropython-ulogger
Author: M-Jay
Author-email: m-jay-1376@qq.com
License: UNKNOWN
Keywords: micropython
Platform: UNKNOWN
Classifier: Development Status :: 5 - Production/Stable
